codeclip/__init__.py
codeclip-0.0.0.dist-info/LICENSE
codeclip-0.0.0.dist-info/METADATA
codeclip-0.0.0.dist-info/WHEEL
codeclip-0.0.0.dist-info/top_level.txt
codeclip-0.0.0.dist-info/RECORD
