Metadata-Version: 2.1
Name: codeclip
Version: 0.0.0
Summary: A powerful templating tool for your projects.
Home-page: https://github.com/parafoxia/codeclip
Author: Ethan Henderson
Author-email: ethan.henderson.1998@gmail.com
License: BSD 3-Clause 'New' or 'Revised' License
Project-URL: Documentation, https://codeclip.readthedocs.io
Project-URL: Source, https://github.com/parafoxia/codeclip
Project-URL: Bug Tracker, https://github.com/parafoxia/codeclip/issues
Project-URL: CI, https://github.com/parafoxia/codeclip/actions
Project-URL: Changelog, https://github.com/parafoxia/codeclip/releases
Classifier: Development Status :: 1 - Planning
Classifier: Environment :: Console
Classifier: Intended Audience :: Developers
Classifier: Intended Audience :: End Users/Desktop
Classifier: License :: OSI Approved :: BSD License
Classifier: Natural Language :: English
Classifier: Operating System :: MacOS
Classifier: Operating System :: Microsoft :: Windows
Classifier: Operating System :: OS Independent
Classifier: Operating System :: POSIX
Classifier: Operating System :: Unix
Classifier: Programming Language :: Python :: 3
Classifier: Programming Language :: Python :: 3 :: Only
Classifier: Programming Language :: Python :: 3.7
Classifier: Programming Language :: Python :: 3.8
Classifier: Programming Language :: Python :: 3.9
Classifier: Programming Language :: Python :: 3.10
Classifier: Programming Language :: Python :: 3.11
Classifier: Programming Language :: Python :: Implementation :: CPython
Classifier: Programming Language :: Python :: Implementation :: PyPy
Classifier: Topic :: Software Development :: Code Generators
Classifier: Topic :: Utilities
Classifier: Typing :: Typed
Requires-Python: >=3.7.0,<3.12
License-File: LICENSE
